

关于写这篇文章，是来自于一个同学在群里抛出这么一道面试题，问执行结果是什么？

```java
public class OverloadTest {


    static abstract class A{}

    static class B extends A {}

    static class C extends A {}

    public void sayHello(A a){
        System.out.println("a");
    }

    public void sayHello(B a){
        System.out.println("b");
    }

    public void sayHello(C b){
        System.out.println("c");
    }

    // Object 参数
    public void say(Object arg) {
        System.out.println("hello object");
    }


    // int 参数
    public void say(int arg) {
        System.out.println("hello int");
    }

    // long 参数
    public void say(long arg) {
        System.out.println("hello long");
    }

    // char 参数
    public void say(char arg) {
        System.out.println("hello char");
    }

    // Character 参数
    public void say(Character arg) {
        System.out.println("hello character");
    }

    // 变长参数
    public void say(char... arg) {
        System.out.println("hello char...");
    }

    // Serializable 参数
    public void say(Serializable arg) {
        System.out.println("hello serializable");
    }


    public static void main(String[] args) {
        OverloadTest overloadTest = new OverloadTest();
        overloadTest.say('a');
        overloadTest.say("a");

        A b = new B();
        A c = new C();
        overloadTest.sayHello(b);
        overloadTest.sayHello(c);
        overloadTest.sayHello((B)b);
    }
}
```

输出的结果如下。

```text
hello char
hello serializable
a
a
b
```

很明显涉及到方法重载（overload），为什么会是这个结果？要从我们开始学Java的时说起，那时老师就告诉我们两个结论。

1. javac编译器在编译阶段会根据参数的静态类型来决定选择哪个重载版本。
2. 重载优先级，先匹配参数个数；再匹配参数类型的直接所属类；如果没有找到直接的所属类，会向上转型（包装类 -> 父类 -> 接口）；如果向上转型无果，再查找可变参数列表；以上都找不到，则报找不到方法错误。

上面提到了静态类型，我举列说明一下。

```text
A b = new B();
```

这里的A就是静态类型，编译阶段可确定；那么相反B就是实际类型，只能运行阶段才能确定。

我估计知道答案的同学很多，但要搞明白整个底层原理的同学很少，这里涉及到Java方法底层调用的原理。

**方法调用**

其实说白了，JVM调用Java程序时，其实也是执行的机器指令，利用字节码解释器作为跨越字节码与机器指令的桥梁，也就是说一个字节码对应一段特定逻辑的本地机器指令，而JVM在解释执行字节码指令时，会直接调用字节码所对应的机器指令。关于它是怎么调用的？如果你感兴趣的话，可以去了解一下C的函数指针，它其实就是将函数指针指向这段机器指令的首地址，从而实现C语言直接调用机器指令的目的（以前写exp经常这么干）。

我承认上面这段，有点难。

简而言之，Java调用方法其实用到了字节码指令，最终查找相应的机器指令，来实现方法的调用。

那么关于方法调用，Java提供了5个字节码指令。

1. invokestatic：调用类方法（编译阶段确定方法调用版本）。
2. invokespecial：调用构造器方法、私有方法及父类方法（编译阶段确定方法调用版本）。
3. invokevirtual：调用实例方法（虚方法）。
4. invokeinterface：调用接口方法，在运行再确定一个实现此接口的对象。
5. invokedynamic：由用户引导方法决定。

invokestatic和invokespecial指令在类加载时，就能把符号引用（即逻辑地址，与虚拟机内存无关）解析为直接引用，符合这个条件的有静态方法、实例构造器方法、私有方法、父类方法这4类，叫非虚方法。

非虚方法除了上面静态方法、实例构造器方法、私有方法、父类方法这4种方法之外，还包括final方法。虽然final方法使用invokevirtual指令来调用，但是final方法无法被覆盖，没有其他版本，无需对方法接收者进行多态选择，或者说多态选择的结果是唯一的。

**底层实现**

要看它底层的实现，我们还是得要看字节码，我通过javap工具把main方法的字节码给各位展示出来，如下所示。

```java
public static void main(java.lang.String[]);
    descriptor: ([Ljava/lang/String;)V
    flags: ACC_PUBLIC, ACC_STATIC
    Code:
      stack=2, locals=4, args_size=1
         0: new           #14                 // class com/yrzx404/base/code/OverloadTest
         3: dup
         4: invokespecial #15                 // Method "<init>":()V
         7: astore_1
         8: aload_1
         9: bipush        97
        11: invokevirtual #16                 // Method say:(C)V
        14: aload_1
        15: ldc           #3                  // String a
        17: invokevirtual #17                 // Method say:(Ljava/io/Serializable;)V
        20: new           #18                 // class com/yrzx404/base/code/OverloadTest$B
        23: dup
        24: invokespecial #19                 // Method com/yrzx404/base/code/OverloadTest$B."<init>":()V
        27: astore_2
        28: new           #20                 // class com/yrzx404/base/code/OverloadTest$C
        31: dup
        32: invokespecial #21                 // Method com/yrzx404/base/code/OverloadTest$C."<init>":()V
        35: astore_3
        36: aload_1
        37: aload_2
        38: invokevirtual #22                 // Method sayHello:(Lcom/yrzx404/base/code/OverloadTest$A;)V
        41: aload_1
        42: aload_3
        43: invokevirtual #22                 // Method sayHello:(Lcom/yrzx404/base/code/OverloadTest$A;)V
        46: aload_1
        47: aload_2
        48: checkcast     #18                 // class com/yrzx404/base/code/OverloadTest$B
        51: invokevirtual #23                 // Method sayHello:(Lcom/yrzx404/base/code/OverloadTest$B;)V
        54: return
      LineNumberTable:
        line 67: 0
        line 68: 8
        line 69: 14
        line 71: 20
        line 72: 28
        line 73: 36
        line 74: 41
        line 75: 46
        line 76: 54
      LocalVariableTable:
        Start  Length  Slot  Name   Signature
            0      55     0  args   [Ljava/lang/String;
            8      47     1 overloadTest   Lcom/yrzx404/base/code/OverloadTest;
           28      27     2     b   Lcom/yrzx404/base/code/OverloadTest$A;
           36      19     3     c   Lcom/yrzx404/base/code/OverloadTest$A;
```

我们这段字节码指令可以得出，invokevirtual已经确定了调用方法，并且是根据方法参数的静态类型来决定的。

这里也解决了之前大家的疑问，overloadTest.sayHello((B)b)，为什么结果为b？主要在这两句字节码指令起的作用。

```java
48: checkcast     #18                 // class com/yrzx404/base/code/OverloadTest$B
51: invokevirtual #23                 // Method sayHello:(Lcom/yrzx404/base/code/OverloadTest$B;)V
```

即在强制类型转换时，会有指令checkcast的调用，而且invokevirtual指令的调用方法也会发生了变化。

关于重写优先级，这是詹爷他们定下的规定，没有什么好说的，记住就好了。

**最后**

相信看到这里，大家应该明白了方法重载。说实话，我个人觉得这道面试题除了为难面试者，没有什么鸟用！因为实际工作中，没有谁闲的蛋疼去写这种“炫技”的代码。

那么关于方法重写（override），我这里给一个结论吧，重写方法的调用主要看实际类型，在运行时决定调用版本。实际类型如果实现了该方法则直接调用该方法，如果没有实现，则在继承关系中从低到高搜索有无实现。

那么，希望你也能就这我的思路去分析一下方法重写

https://www.zhihu.com/tardis/sogou/art/58429562

---

https://www.cnblogs.com/tuyang1129/p/12519578.html

## 一、前言

  今天看《深入理解Java虚拟机》这本书的时候，看到了其中对方法重载（`Overload`）以及方法重写（`Override`）的原理讲解，顿时有了恍然大悟之感。这篇博客我就来参考书中的内容，讲一讲方法重载的实现原理。



## 二、正文

###  2.1 什么是方法重载

  讲重载的实现原理之前，还是先来说一说什么是方法重载。`Java`中的每一个方法，都有自己的签名，或者也可以叫做标识，用来确认它的唯一性。**在同一个类中，不能出现两个签名一样的方法**。而方法的签名由什么组成呢？答案是**方法名称 + 参数列表**，也就是说，一个类中不允许出现两个方法名称一样，而且方法的参数列表也一样的方法（一个`static`，一个非`static`也不行）。知道上面的概念后，我们就可以定义方法重载了：**在同一个类中，拥有相同方法名称，但是不同参数列表的多个方法，被称为重载方法，这种形式被称为方法的重载**。例如下面几个方法，就是重载的方法，它们拥有相同的名称，但是参数列表不同：



```java
void test(int a) {
    System.out.println("type int");
}

void test(String a) {
    System.out.println("type String");
}

void test(String arg1, int arg2){
    System.out.println("String + int");
}

void test(int arg1, String arg2){
    System.out.println("int + String");
}
```

  需要注意的是，参数列表的不同指的是参数的数量不同，或者在参数数量相同的情况下，相同位置的参数类型不同，比如上面最后两个方法，虽然参数都是一个`String`，一个`int`，但是位置不同，所以也是允许的。可以注意到，最后两个方法的参数名称都是`arg1`和`arg2`，且位置相同，但是并不影响，因为方法的签名和参数的名称无关，只和类型有关。

  最后需要注意的一点是，返回值并不能作为方法的重载条件，比如下面两个方法：



```java
// 无返回值
void test(int a) {
    System.out.println("type int");
}

// 返回值为int
int test(int a) {
    return a;
}
```

  若一个类中同时出现以下两个方法，将会编译错误，因为它们的方法名称+参数列表是一致的，编译器无法识别。为什么返回值不能作为重载的依据呢？很简单，因为我们调用方法时，并不一定需要接收方法的返回值，比如下面这行代码，对于上面两个方法都是适用的，编译器无法确定选择哪一个：



```java
public static void main (String[]args){
    test(1);
}
```



###  2.2 如何选择调用哪一个重载方法

  当出现多个重载的方法时，编译器如何决定调用哪一个被重载的方法呢？相信很多人都知道，是**根据调用方法时传递的实际参数类型来确定**。比如说最开始列举的四个`test`方法，如果我们使用`test（1）`，那将调用`void test(int a)`这个方法；如果我们使用`test("aaa")`，那将调用`void test(String a)`这个方法。这个应该很好理解，编译器在编译期间，根据调用方法的实际参数类型，就能够确定具体需要调用的哪一个方法。但是，这只是一种简单的情况，下面来看看一种稍微复杂的情况，即继承关系下的方法重载（看完后先猜猜输出结果）：



```java
public class Main {
	// 声明一个父类
    static class Human {
    }
    // 声明两个子类
    static class Man extends Human {
    }
    static class Woman extends Human {
    }

    // 三个重载方法，参数类型分别为以上三种类型
    static void sayHello(Human human){
        System.out.println("human say Hello");
    }
    static void sayHello(Man man){
        System.out.println("man say Hello");
    }
    static void sayHello(Woman woman){
        System.out.println("woman say Hello");
    }

    public static void main(String[] args) {
        Human man = new Man();
        Human woman = new Woman();
        sayHello(man);
        sayHello(woman);
    }
}
```

  以上代码的输出结果如下：



```java
human say Hello
human say Hello
```

  根据结果可以看到，最终都调用了参数为父类型`Man`的`sayHello`方法。这是为什么呢？这是因为**对重载方法的选择，是根据变量的静态类型来确定的，而不是实际类型**。比如代码`Human man = new Man()`，`Human`就是变量`man`的静态类型，而`Man`是它的实际类型。我们都知道，在多态的情况下调用方法，会根据实际类型调用实际对象的方法，但是在重载中，是根据静态类型来确定调用哪一个方法的。在上面的代码中，`man`和`woman`对象的静态类型都是`Human`，所以都调用`static void sayHello(Human human)`方法。和调用重写方法不同，由于一个对象的静态类型在编译期间就可以确定，所以调用哪个重载方法是在编译期就确定好了，这叫**静态分派**，而调用重写的方法却要在运行时才能确定具体类型，这叫**动态分派**。



###  2.3 重载调用的优先级

  接下来，我们再来看一个更加复杂的情况，如下代码：



```java
public class Test {

    static void sayHello(char arg) {
        System.out.println("hello, char");
    }

    static void sayHello(int arg) {
        System.out.println("hello, int");
    }

    static void sayHello(long arg) {
        System.out.println("hello, long");
    }

    static void sayHello(Character arg) {
        System.out.println("hello, Character");
    }

    static void sayHello(Serializable org) {
        System.out.println("hello, Serializable");
    }

    static void sayHello(Object arg) {
        System.out.println("hello, object");
    }

    static void sayHello(char... org) {
        System.out.println("hello, char...");
    }

    public static void main(String[] args) {
        sayHello('a');
    }
}
```

  上面对`sayHello`方法重载了七次，这七个重载方法都只有一个参数，但是参数的类型各不相同。在`main`方法中，我们调用`sayHello`方法，并传入一个字符`'a'`，结果不出意料，输出如下：



```java
"hello, char"
```

  这个结果应该不会有意外，毕竟`'a'`就是一个字符，调用参数为`char`的方法合情合理。接着，我们将`sayHello(char arg)`方法注释掉，再来看看运行结果：



```
"hello, int"
```

  当参数为`char`的方法被注释后，编译器选择了参数为`int`的方法。这也不难理解，这里发生了自动类型转换，将字符`a`转换成了它的`Unicode`编码（97），因此调用`sayHello(int arg)`是合适的。接着，我们将`sayHello(int arg)`也注释掉，看看输出结果：



```
"hello, long"
```

  这时候调用了参数类型为`long`的方法，也就是说这里发生了两次转换，先将`a`转换成`int`类型的`97`，再将`97`转换为`long`类型的`97L`，接着再调用相应的方法。上面的代码中我没有写参数为`float`和`double`的方法，不然这种转换还会继续，而顺序是`char->int->long->float->double`。但是不会被转换成`byte`和`short`，因为这不是安全的转换，`byte`只有一个字节，而`char`有两个字节，所以不行；而`short`虽然有两个字节，但是有一半是负数，`char`的编码不存在负数，所以也不行。好了，接下来我们将`sayHello(long arg)`也注释，看看结果：



```
"hello, Character"
```

  根据结果可以发现，这里发生了一次自动装箱，将`a`封装成了一个`Character`对象，然后调用了相应的方法。这也是合情合理的。然后，我们再注释`sayHello(Character arg)`方法，再次运行：



```
"hello, Serializable"
```

  先在这个结果就有一点迷惑了，这么连`Serializable`都行？这是因为`Character`类实现了`Serializable`接口，也就是说这里发生了两次转换，先将`'a'`封装成`Character`对象，再转型成为它的父类型`Serializable`。所以，当我们调用重载的方法时，如果不存在对应的类型，则编译器会从下往上，依次寻找当前类型的父类型，直到找到第一个父类型满足某一个重载方法为止，若直到最后都没有找到，就会编译错误。`Character`类实现了两个接口，一个是`Serializable`，一个是`Comparable<Character>`，如果同时存在这两个参数类型的重载方法，编译器将会报错，因为这两个类型是同级别的，不知道该选择哪一个。这种情况下，我们可以使用显示的类型转换，来选择需要调用的方法。好了，我们现在将`sayHello(Serializable org)`也注释，看看结果：



```
"hello, object"
```

  可以看到，这时候调用了参数类型为`Object`的重载方法。这正好验证了我们上面说的结论——从下往上寻找父类型的重载方法，因为`Object`就是所有类的父类（除了`Object`本身）。然后，我们再注释`sayHello(Object arg)` ：



```
"hello, char..."
```

  可以看到，调用了可变参数类型的方法，这时候的`a`被当成了一个数组元素。所以，可变成参数类型的优先级是最低的。如果此时还有一个`sayHello(int... org)`，则在注释完`sayHello(char... org)`后，将调用它，正好又对应上了我们前面说的 `char->int->long->float->double`的顺序，这个顺序在可变长类型中也适用。

  说到这里，我们应该能够明白，**在方法调用有多个选择的情况下，编译器总是会根据优先级，选择最适合的那个**。而关于这个优先级如何决定，可以去看看`Java`语言规范，其中对这部分做了详细规定。



## 三、总结

  说了这么多，最关键的一点还是：重载是根据变量的静态类型进行选择的。只要理解了这一点，对于重载也就很容易弄懂了。最后还要说一点，无论对重载理解有多么深刻，想最后一个例子中这样模棱两可的代码还是不要写为好，毕竟可（rong）读（yi）性（ai）太（da）差了。希望这篇博客对想要了解重载的人有所帮助吧。



## 四、参考

- 《深入理解Java虚拟机》



---

https://www.cnblogs.com/kaleidoscope/p/9790766.html

https://www.cnblogs.com/startRuning/p/5673485.html

